pymisclib/__init__.py
pymisclib/__version__.py
pymisclib/ansiterminal.py
pymisclib/ascii_table.py
pymisclib/chunkystreamsocket.py
pymisclib/commandmenu.py
pymisclib/deadlinequeue.py
pymisclib/dolcenum.py
pymisclib/enumaction.py
pymisclib/hardwareregister.py
pymisclib/littlejonny.py
pymisclib/multiprogressbar.py
pymisclib/package.spdx
pymisclib/prefixes.py
pymisclib/ringbuffer.py
pymisclib/time_t.py
pymisclib/unicodechars.py
pymisclib/utilities.py
pymisclib/xmlutils.py
pymisclib-1.7.3.dist-info/licenses/LICENSE
pymisclib-1.7.3.dist-info/METADATA
pymisclib-1.7.3.dist-info/WHEEL
pymisclib-1.7.3.dist-info/top_level.txt
pymisclib-1.7.3.dist-info/RECORD
