Metadata-Version: 2.4
Name: pymisclib
Version: 1.7.3
Summary: A collection of various useful Python routines.
Author-email: Christian Dönges <cd.pymisclib@platypus-projects.net>
License-Expression: Apache-2.0
Project-URL: Homepage, https://rot.regenbogenkraut.de/cd/pymisclib
Project-URL: Bug Tracker, https://rot.regenbogenkraut.de/cd/pymisclib/issues
Classifier: Programming Language :: Python :: 3
Classifier: Operating System :: OS Independent
Requires-Python: >=3.9
License-File: LICENSE
Dynamic: license-file
